nemotron_quick/__main__.py
nemotron_quick-0.0.1.dist-info/METADATA
nemotron_quick-0.0.1.dist-info/WHEEL
nemotron_quick-0.0.1.dist-info/entry_points.txt
nemotron_quick-0.0.1.dist-info/RECORD
