Metadata-Version: 2.4
Name: nemotron-quick
Version: 0.0.1
Summary: Quick nemotron wrapper with key included
Requires-Python: >=3.8
Requires-Dist: requests
